pydra/tasks/mrtrix3/__init__.py
pydra/tasks/mrtrix3/_version.py
pydra/tasks/mrtrix3/base.py
pydra/tasks/mrtrix3/conftest.py
pydra/tasks/mrtrix3/utils.py
pydra/tasks/mrtrix3/tests/__init__.py
pydra/tasks/mrtrix3/tests/test_utils.py
pydra_mrtrix3-0.2.1.dist-info/LICENSE
pydra_mrtrix3-0.2.1.dist-info/METADATA
pydra_mrtrix3-0.2.1.dist-info/WHEEL
pydra_mrtrix3-0.2.1.dist-info/top_level.txt
pydra_mrtrix3-0.2.1.dist-info/RECORD
